ragstack/__init__.py
ragstack/ragstack.py
ragstack-0.0.1.dist-info/METADATA
ragstack-0.0.1.dist-info/WHEEL
ragstack-0.0.1.dist-info/top_level.txt
ragstack-0.0.1.dist-info/RECORD
