Metadata-Version: 2.1
Name: ragstack
Version: 0.0.1
Summary: Ragstack is a one-click solution to deploy the retrieval augmented generation stack on your own infrastructure with open-source LLMs.
Author: Ayan Bandyopadhyay
Author-email: ayan@psychic.dev
Requires-Dist: requests
